{"lastUsed":1684270447285,"path":"C:\/workspace\/d01 meus estudos\/meus-estudos-d01\/SistemaTv","projectCount":1,"recentFiles":[{"path":"\/ProjetoTv\/src\/main\/java\/tv","parentWorkspace":"C:\/workspace\/d01 meus estudos\/meus-estudos-d01\/SistemaTv","name":"Usuario.java","lastModified":1684270447287,"locationURI":"file:\/C:\/workspace\/d01%20meus%20estudos\/meus-estudos-d01\/SistemaTv\/ProjetoTv\/src\/main\/java\/tv\/Usuario.java"},{"path":"\/ProjetoTv\/src\/main\/java\/tv","parentWorkspace":"C:\/workspace\/d01 meus estudos\/meus-estudos-d01\/SistemaTv","name":"SmartTv.java","lastModified":1684270124083,"locationURI":"file:\/C:\/workspace\/d01%20meus%20estudos\/meus-estudos-d01\/SistemaTv\/ProjetoTv\/src\/main\/java\/tv\/SmartTv.java"}]}